pytrycatch/__init__.py
pytrycatch/execptions.py
pytrycatch/handlers.py
pytrycatch/utils.py
pytrycatch-0.0.3.dist-info/LICENSE
pytrycatch-0.0.3.dist-info/METADATA
pytrycatch-0.0.3.dist-info/WHEEL
pytrycatch-0.0.3.dist-info/top_level.txt
pytrycatch-0.0.3.dist-info/RECORD
